netbox_plugin_bind_provisioner/__init__.py
netbox_plugin_bind_provisioner/models.py
netbox_plugin_bind_provisioner/utils.py
netbox_plugin_bind_provisioner/management/commands/bind-transfer-endpoint.py
netbox_plugin_bind_provisioner/management/commands/export-all-dns-zones.py
netbox_plugin_bind_provisioner/management/commands/export-dns-zone.py
netbox_plugin_bind_provisioner/migrations/0001_initial.py
netbox_plugin_bind_provisioner/migrations/0002_alter_integerkeyvaluesetting_options_and_more.py
netbox_plugin_bind_provisioner/migrations/__init__.py
netbox_plugin_bind_provisioner-1.0.5.dist-info/licenses/LICENSE.md
netbox_plugin_bind_provisioner-1.0.5.dist-info/METADATA
netbox_plugin_bind_provisioner-1.0.5.dist-info/WHEEL
netbox_plugin_bind_provisioner-1.0.5.dist-info/top_level.txt
netbox_plugin_bind_provisioner-1.0.5.dist-info/RECORD
