Metadata-Version: 2.4
Name: netbox-plugin-bind-provisioner
Version: 1.0.5
Summary: A Bind provisioning plugin that uses netbox_dns for its data source
Author: Sven Luethi
License: GPL-2.0
Project-URL: Homepage, https://github.com/Suraxius/netbox-plugin-bind-provisioner
Project-URL: Issues, https://github.com/Suraxius/netbox-plugin-bind-provisioner/issues
Requires-Python: >=3.7
License-File: LICENSE.md
Requires-Dist: netbox-plugin-dns
Dynamic: license-file
